geode_implicitmodeling/__init__.py
geode_implicitmodeling/explicitation.py
geode_implicitmodeling/geode_implicitmodeling.py
geode_implicitmodeling/geode_implicitmodeling_explicitation.py
geode_implicitmodeling/geode_implicitmodeling_implicitation.py
geode_implicitmodeling/geode_implicitmodeling_insertion.py
geode_implicitmodeling/geode_implicitmodeling_io.py
geode_implicitmodeling/geode_implicitmodeling_model.py
geode_implicitmodeling/implicitation.py
geode_implicitmodeling/insertion.py
geode_implicitmodeling/io.py
geode_implicitmodeling/model.py
Geode_ImplicitModeling-1.16.1.dist-info/METADATA
Geode_ImplicitModeling-1.16.1.dist-info/WHEEL
Geode_ImplicitModeling-1.16.1.dist-info/top_level.txt
Geode_ImplicitModeling-1.16.1.dist-info/RECORD
