Metadata-Version: 2.1
Name: Geode-ImplicitModeling
Version: 1.16.1
Summary: Licensed framework for working with implicit modeling
Home-page: https://github.com/Geode-solutions/Geode-ImplicitModeling
Author: Geode-solutions
Author-email: contact@geode-solutions.com
License: Proprietary
